arxiv/arxiv_cleaner.py
arxiv/run_clean.py
arxiv/run_download.py
arxiv/token_count.py
arxiv/utils.py
book/__init__.py
book/dedup.py
book/download.py
book/token_count.py
c4/__init__.py
c4/c4_reformat.py
cc/cc_net/setup.py
cc/cc_net/cc_net/__init__.py
cc/cc_net/cc_net/__main__.py
cc/cc_net/cc_net/dedup.py
cc/cc_net/cc_net/execution.py
cc/cc_net/cc_net/flat_hash_set.py
cc/cc_net/cc_net/get_wiki_cirrus.py
cc/cc_net/cc_net/jsonql.py
cc/cc_net/cc_net/mine.py
cc/cc_net/cc_net/minify.py
cc/cc_net/cc_net/perplexity.py
cc/cc_net/cc_net/process_wet_file.py
cc/cc_net/cc_net/regroup.py
cc/cc_net/cc_net/split_by_lang.py
cc/cc_net/cc_net/text_normalizer.py
cc/cc_net/cc_net/tokenizer.py
cc/cc_net/cc_net/tools/__init__.py
cc/cc_net/cc_net/tools/dl_cc_100.py
cc/cc_net/cc_net/tools/expand_corpus.py
cc/cc_net/cc_net/tools/make_dmoz_corpus.py
cc/cc_net/tests/__init__.py
cc/cc_net/tests/conftest.py
cc/cc_net/tests/test_dedup.py
cc/cc_net/tests/test_flat_hash_set.py
cc/cc_net/tests/test_jsonql.py
cc/cc_net/tests/test_minify.py
cc/cc_net/tests/test_normalizer.py
cc/cc_net/tests/test_parse_wet_file.py
cc/cc_net/tests/test_regroup.py
cc/cc_net/tests/test_transformer.py
cc/classifier/classify.py
cc/classifier/create_corpus.py
cc/dedup/dedup_phase1.py
cc/dedup/dedup_phase2.py
github/__init__.py
github/github_clean_dedup_local.py
github/github_global_dedup.py
github/github_merge_dedup.py
github/github_run_filter.py
github/github_token_count.py
stack_exchange/__init__.py
stack_exchange/count.py
stack_exchange/download.py
stack_exchange/filter.py
stack_exchange/post_processing.py
stack_exchange/print_stats.py
stack_exchange/token_count.py
wikipedia/__init__.py
wikipedia/convert_format.py
wikipedia/download.py
wikipedia/token_count.py
redpajama-0.0.1.dist-info/LICENSE
redpajama-0.0.1.dist-info/METADATA
redpajama-0.0.1.dist-info/WHEEL
redpajama-0.0.1.dist-info/top_level.txt
redpajama-0.0.1.dist-info/RECORD
